lb/nightly/rpc/__init__.py
lb/nightly/rpc/_task_helpers.py
lb/nightly/rpc/archs.py
lb/nightly/rpc/beat.py
lb/nightly/rpc/scheduler.py
lb/nightly/rpc/tasks.py
lb/nightly/rpc/work_env.py
lb_nightly_rpc-0.2.1.dist-info/LICENSE
lb_nightly_rpc-0.2.1.dist-info/WHEEL
lb_nightly_rpc-0.2.1.dist-info/METADATA
lb_nightly_rpc-0.2.1.dist-info/RECORD
